quickprofile/__init__.py
quickprofile/profiler.py
tests/__init__.py
tests/test_profiler.py
quickprofile-0.2.0.dist-info/METADATA
quickprofile-0.2.0.dist-info/WHEEL
quickprofile-0.2.0.dist-info/top_level.txt
quickprofile-0.2.0.dist-info/RECORD
